LICENSE
MANIFEST.in
NOTICE
README.rst
setup.cfg
setup.py
doc/conf.py
doc/index.rst
doc/vas.gemfire.rst
doc/vas.rabbitmq.rst
doc/vas.rst
doc/vas.shared.rst
doc/vas.sqlfire.rst
doc/vas.tc_server.rst
doc/vas.vfabric.rst
doc/vas.web_server.rst
doc/_static/.gitignore
examples/bootstrap-agent/README.rst
examples/bootstrap-agent/bootstrap_agent.py
examples/rabbitmq/management-plugin/README.rst
examples/rabbitmq/management-plugin/management-plugin.py
examples/tc-server/configuration/README.rst
examples/tc-server/configuration/configuration.py
examples/tc-server/web-application/README.rst
examples/tc-server/web-application/web_application.py
test-responses/gemfire/application-code-images-detail.json
test-responses/gemfire/application-code-images-list.json
test-responses/gemfire/groups-agent-instances-configurations-live-content.txt
test-responses/gemfire/groups-agent-instances-configurations-live-detail.json
test-responses/gemfire/groups-agent-instances-configurations-live-list.json
test-responses/gemfire/groups-agent-instances-configurations-pending-content.txt
test-responses/gemfire/groups-agent-instances-configurations-pending-detail.json
test-responses/gemfire/groups-agent-instances-configurations-pending-list.json
test-responses/gemfire/groups-agent-instances-detail.json
test-responses/gemfire/groups-agent-instances-list.json
test-responses/gemfire/groups-agent-instances-state.json
test-responses/gemfire/groups-cache-server-instances-application-code-live-detail.json
test-responses/gemfire/groups-cache-server-instances-application-code-live-list.json
test-responses/gemfire/groups-cache-server-instances-application-code-pending-detail.json
test-responses/gemfire/groups-cache-server-instances-application-code-pending-list.json
test-responses/gemfire/groups-cache-server-instances-configurations-live-content.txt
test-responses/gemfire/groups-cache-server-instances-configurations-live-detail.json
vas.egg-info/PKG-INFO
vas.egg-info/SOURCES.txt
vas.egg-info/dependency_links.txt
vas.egg-info/requires.txt
vas.egg-info/top_level.txt
